<DsRadarCalib>
  <radarName>SPOL</radarName>
  <calibTime>2019-10-26T23:46:37</calibTime>
  <wavelengthCm>10.6726</wavelengthCm>
  <beamWidthDegH>0.92</beamWidthDegH>
  <beamWidthDegV>0.92</beamWidthDegV>
  <antGainDbH>44.95</antGainDbH>
  <antGainDbV>45.32</antGainDbV>
  <pulseWidthUs>1</pulseWidthUs>
  <xmitPowerDbmH>88.16</xmitPowerDbmH>
  <xmitPowerDbmV>88.2</xmitPowerDbmV>
  <twoWayWaveguideLossDbH>1.16</twoWayWaveguideLossDbH>
  <twoWayWaveguideLossDbV>1.44</twoWayWaveguideLossDbV>
  <twoWayRadomeLossDbH>0</twoWayRadomeLossDbH>
  <twoWayRadomeLossDbV>0</twoWayRadomeLossDbV>
  <receiverMismatchLossDb>0.37</receiverMismatchLossDb>
  <kSquaredWater>0.93</kSquaredWater>
  <radarConstH>69.0658</radarConstH>
  <radarConstV>68.5658</radarConstV>
  <noiseDbmHc>-79.1062</noiseDbmHc>
  <noiseDbmHx>-78.9385</noiseDbmHx>
  <noiseDbmVc>-79.2269</noiseDbmVc>
  <noiseDbmVx>-78.9686</noiseDbmVx>
  <i0DbmHc>-113.842</i0DbmHc>
  <i0DbmHx>-113.864</i0DbmHx>
  <i0DbmVc>-114.244</i0DbmVc>
  <i0DbmVx>-114.281</i0DbmVx>
  <receiverGainDbHc>34.7362</receiverGainDbHc>
  <receiverGainDbHx>34.9257</receiverGainDbHx>
  <receiverGainDbVc>35.017</receiverGainDbVc>
  <receiverGainDbVx>35.3122</receiverGainDbVx>
  <receiverSlopeDbHc>1.00122</receiverSlopeDbHc>
  <receiverSlopeDbHx>1.00074</receiverSlopeDbHx>
  <receiverSlopeDbVc>1.0012</receiverSlopeDbVc>
  <receiverSlopeDbVx>1.00073</receiverSlopeDbVx>
  <dynamicRangeDbHc>90.2572</dynamicRangeDbHc>
  <dynamicRangeDbHx>89.9763</dynamicRangeDbHx>
  <dynamicRangeDbVc>90.4581</dynamicRangeDbVc>
  <dynamicRangeDbVx>90.1314</dynamicRangeDbVx>
  <baseDbz1kmHc>-44.7765</baseDbz1kmHc>
  <baseDbz1kmHx>-44.7984</baseDbz1kmHx>
  <baseDbz1kmVc>-45.678</baseDbz1kmVc>
  <baseDbz1kmVx>-45.715</baseDbz1kmVx>
  <sunPowerDbmHc>-9999</sunPowerDbmHc>
  <sunPowerDbmHx>-9999</sunPowerDbmHx>
  <sunPowerDbmVc>-9999</sunPowerDbmVc>
  <sunPowerDbmVx>-9999</sunPowerDbmVx>
  <noiseSourcePowerDbmH>-40</noiseSourcePowerDbmH>
  <noiseSourcePowerDbmV>-40</noiseSourcePowerDbmV>
  <powerMeasLossDbH>5.67</powerMeasLossDbH>
  <powerMeasLossDbV>5.97</powerMeasLossDbV>
  <couplerForwardLossDbH>36.9</couplerForwardLossDbH>
  <couplerForwardLossDbV>36.7</couplerForwardLossDbV>
  <dbzCorrection>0</dbzCorrection>
  <zdrCorrectionDb>0</zdrCorrectionDb>
  <ldrCorrectionDbH>0</ldrCorrectionDbH>
  <ldrCorrectionDbV>0</ldrCorrectionDbV>
  <systemPhidpDeg>0</systemPhidpDeg>
  <testPowerDbmH>-9999</testPowerDbmH>
  <testPowerDbmV>-9999</testPowerDbmV>
</DsRadarCalib>
